tigriscalc/__init__.py
tigriscalc/tigriscalc.py
tigriscalc-0.0.3.dist-info/METADATA
tigriscalc-0.0.3.dist-info/WHEEL
tigriscalc-0.0.3.dist-info/top_level.txt
tigriscalc-0.0.3.dist-info/RECORD
