Metadata-Version: 2.1
Name: tigriscalc
Version: 0.0.3
Summary: A package contains basic to advance math functions
Author: Aradhya Kaushal
Author-email: kaushalaradhya789@gmail.com
Keywords: python,math
Classifier: Development Status :: 1 - Planning
Classifier: Intended Audience :: Developers
Classifier: Programming Language :: Python :: 3
Classifier: Operating System :: Unix
Classifier: Operating System :: MacOS :: MacOS X
Classifier: Operating System :: Microsoft :: Windows
